{
  "config": {
    "keyframeSavePeriod": 4,
    "physicsDeactivationTime": 0.75,
    "placementSearchHeight": 0.5,
    "pickerSphereRadius": 0.05,
    "link": {
      "divisionEps": 0.009,
      "distEps": 0.02,
      "maxVelMag": 20.0,
      "baseVelMag0": 0.2,
      "baseVelMag1": 0.05,
      "rampUpTime": 2.0
    },
    "colors": {
      "goodPlacement": [
        0.0,
        1.0,
        0.0,
        1.0
      ],
      "badPlacement": [
        1.0,
        0.0,
        0.0,
        1.0
      ],
      "artObj": [
        1.0,
        0.5,
        0.0,
        1.0
      ],
      "rigidObj": [
        1.0,
        0.0,
        0.0,
        1.0
      ],
      "placementGuide": [
        0.0,
        1.0,
        0.0,
        0.3
      ]
    },
    "cameras": [
      {
        "eye": [
          -1.059,
          1.5,
          1.799
        ],
        "lookat": [
          -1.059,
          0.2,
          0.2
        ]
      },
      {
        "eye": [
          -0.72,
          0.899,
          1.299
        ],
        "lookat": [
          -1.059,
          0.5,
          1.0
        ]
      },
      {
        "eye": [
          -0.54,
          1.299,
          1.0
        ],
        "lookat": [
          -1.32,
          0.2,
          1.0
        ]
      },
      {
        "eye": [
          -1.6,
          1.299,
          1.0
        ],
        "lookat": [
          -0.899,
          0.2,
          1.0
        ]
      },
      {
        "eye": [
          -1.399,
          0.899,
          1.299
        ],
        "lookat": [
          -1.059,
          0.5,
          1.0
        ]
      }
    ]
  }
}